fabricatio_checkpoint/__init__.py
fabricatio_checkpoint/actions/__init__.py
fabricatio_checkpoint/capabilities/__init__.py
fabricatio_checkpoint/capabilities/checkpoint.py
fabricatio_checkpoint/cli.py
fabricatio_checkpoint/config.py
fabricatio_checkpoint/inited_service.py
fabricatio_checkpoint/models/__init__.py
fabricatio_checkpoint/models/checkpoint.py
fabricatio_checkpoint/py.typed
fabricatio_checkpoint/rust.cpython-314-x86_64-linux-gnu.so
fabricatio_checkpoint/rust.pyi
fabricatio_checkpoint/workflows/__init__.py
fabricatio_checkpoint-0.3.0.dist-info/METADATA
fabricatio_checkpoint-0.3.0.dist-info/WHEEL
fabricatio_checkpoint-0.3.0.dist-info/entry_points.txt
fabricatio_checkpoint-0.3.0.dist-info/RECORD
